dapla_pseudo/__init__.py
dapla_pseudo/constants.py
dapla_pseudo/exceptions.py
dapla_pseudo/globberator/__init__.py
dapla_pseudo/globberator/traverser.py
dapla_pseudo/models.py
dapla_pseudo/py.typed
dapla_pseudo/types.py
dapla_pseudo/utils.py
dapla_pseudo/v1/__init__.py
dapla_pseudo/v1/baseclasses.py
dapla_pseudo/v1/client.py
dapla_pseudo/v1/depseudo.py
dapla_pseudo/v1/models/api.py
dapla_pseudo/v1/models/core.py
dapla_pseudo/v1/mutable_dataframe.py
dapla_pseudo/v1/pseudo.py
dapla_pseudo/v1/repseudo.py
dapla_pseudo/v1/result.py
dapla_pseudo/v1/supported_file_format.py
dapla_pseudo/v1/validation.py
dapla_toolbelt_pseudo-6.0.1.dist-info/LICENSE
dapla_toolbelt_pseudo-6.0.1.dist-info/METADATA
dapla_toolbelt_pseudo-6.0.1.dist-info/WHEEL
dapla_toolbelt_pseudo-6.0.1.dist-info/RECORD
