Metadata-Version: 2.3
Name: dapla-toolbelt-pseudo
Version: 6.0.1
Summary: Pseudonymization extensions for Dapla
License: MIT
Author: Dapla Developers
Author-email: dapla-platform-developers@ssb.no
Requires-Python: >=3.11,<4.0
Classifier: Development Status :: 4 - Beta
Classifier: License :: OSI Approved :: MIT License
Classifier: Programming Language :: Python :: 3
Classifier: Programming Language :: Python :: 3.11
Classifier: Programming Language :: Python :: 3.12
Classifier: Programming Language :: Python :: 3.13
Requires-Dist: aiohttp (>=3.10.5)
Requires-Dist: aiohttp-retry (>=2.9.1)
Requires-Dist: click (>=8.0.1)
Requires-Dist: cloudpathlib[gs] (>=0.17.0)
Requires-Dist: cryptography (>41.0.0)
Requires-Dist: dapla-auth-client (>=1.2.1)
Requires-Dist: dapla-toolbelt-metadata (>=0.10.5,<1.0.0)
Requires-Dist: deprecated (>=1.2.18)
Requires-Dist: fsspec (>=2023.5.0)
Requires-Dist: gcsfs (>=2025.5.1,<2026.0.0)
Requires-Dist: msgspec (>=0.18.6)
Requires-Dist: numpy (>=1.26.4)
Requires-Dist: orjson (>=3.10.1)
Requires-Dist: pandas-stubs (>=1.5.3.230304)
Requires-Dist: polars (>=1.31.0)
Requires-Dist: puremagic (>=1.15)
Requires-Dist: pyarrow (>=14.0.2)
Requires-Dist: pydantic (>=2.0)
Requires-Dist: pygments (>2.15.0)
Requires-Dist: pyhumps (>=3.8.0)
Requires-Dist: pytest-asyncio (>=0.24.0)
Requires-Dist: python-ulid (>=2.2.0)
Requires-Dist: types-deprecated (>=1.2.15.20250304)
Requires-Dist: types-requests (>=2.28.11)
Requires-Dist: wcmatch (>=8.5.1)
Project-URL: Changelog, https://github.com/statisticsnorway/dapla-toolbelt-pseudo/releases
Project-URL: Documentation, https://statisticsnorway.github.io/dapla-toolbelt-pseudo
Project-URL: Homepage, https://github.com/statisticsnorway/dapla-toolbelt-pseudo
Project-URL: Repository, https://github.com/statisticsnorway/dapla-toolbelt-pseudo
